mpv.py
mpv-1.0.7.dist-info/LICENSE.GPL
mpv-1.0.7.dist-info/LICENSE.LGPL
mpv-1.0.7.dist-info/METADATA
mpv-1.0.7.dist-info/WHEEL
mpv-1.0.7.dist-info/top_level.txt
mpv-1.0.7.dist-info/RECORD
