Metadata-Version: 2.1
Name: mpv
Version: 1.0.7
Summary: A python interface to the mpv media player
Author-email: jaseg <mpv@jaseg.de>
License: GPLv2+ or LGPLv2.1+
Project-URL: homepage, https://github.com/jaseg/python-mpv
Keywords: mpv,library,video,audio,player,display,multimedia
Classifier: Development Status :: 5 - Production/Stable
Classifier: Environment :: X11 Applications
Classifier: Intended Audience :: Developers
Classifier: License :: OSI Approved :: GNU General Public License v2 or later (GPLv2+)
Classifier: License :: OSI Approved :: GNU Lesser General Public License v2 or later (LGPLv2+)
Classifier: Natural Language :: English
Classifier: Operating System :: POSIX
Classifier: Programming Language :: C
Classifier: Programming Language :: Python :: 3.9
Classifier: Programming Language :: Python :: 3.10
Classifier: Programming Language :: Python :: 3.11
Classifier: Programming Language :: Python :: 3.12
Classifier: Topic :: Multimedia :: Sound/Audio :: Players
Classifier: Topic :: Multimedia :: Video :: Display
Requires-Python: >=3.9
License-File: LICENSE.GPL
License-File: LICENSE.LGPL
Provides-Extra: screenshot_raw
Requires-Dist: Pillow ; extra == 'screenshot_raw'
Provides-Extra: test
Requires-Dist: PyVirtualDisplay ; extra == 'test'
